ipol.py
ipol-9.data/data/idl/ace.Dockerfile
ipol-9.data/data/idl/bm3d.Dockerfile
ipol-9.data/data/idl/dctdenoise.Dockerfile
ipol-9.data/data/idl/drunet.Dockerfile
ipol-9.data/data/idl/ffdnet.Dockerfile
ipol-9.data/data/idl/gauss.Dockerfile
ipol-9.data/data/idl/lsd.Dockerfile
ipol-9.data/data/idl/msdctd.Dockerfile
ipol-9.data/data/idl/nlbayes.Dockerfile
ipol-9.data/data/idl/nlm.Dockerfile
ipol-9.data/data/idl/phs.Dockerfile
ipol-9.data/data/idl/scb.Dockerfile
ipol-9.data/data/idl/tvdenoise.Dockerfile
ipol-9.data/data/idl/tvl1.Dockerfile
ipol-9.dist-info/METADATA
ipol-9.dist-info/WHEEL
ipol-9.dist-info/top_level.txt
ipol-9.dist-info/RECORD
